{
  "tracks": [
    {
      "album": {
        "album_type": "album",
        "artists": [
          {
            "external_urls": {
              "spotify": "https://open.spotify.com/artist/2rLGlNI6htigNxx172qxLu"
            },
            "href": "https://api.spotify.com/v1/artists/2rLGlNI6htigNxx172qxLu",
            "id": "2rLGlNI6htigNxx172qxLu",
            "name": "Jane Remover",
            "type": "artist",
            "uri": "spotify:artist:2rLGlNI6htigNxx172qxLu"
          }
        ],
        "available_markets": [
          "AR",
          "AU",
          "AT",
          "BE",
          "BO",
          "BR",
          "BG",
          "CA",
          "CL",
          "CO",
          "CR",
          "CY",
          "CZ",
          "DK",
          "DO",
          "DE",
          "EC",
          "EE",
          "SV",
          "FI",
          "FR",
          "GR",
          "GT",
          "HN",
          "HK",
          "HU",
          "IS",
          "IE",
          "IT",
          "LV",
          "LT",
          "LU",
          "MY",
          "MT",
          "MX",
          "NL",
          "NZ",
          "NI",
          "NO",
          "PA",
          "PY",
          "PE",
          "PH",
          "PL",
          "PT",
          "SG",
          "SK",
          "ES",
          "SE",
          "CH",
          "TW",
          "TR",
          "UY",
          "US",
          "GB",
          "AD",
          "LI",
          "MC",
          "ID",
          "JP",
          "TH",
          "VN",
          "RO",
          "IL",
          "ZA",
          "SA",
          "AE",
          "BH",
          "QA",
          "OM",
          "KW",
          "EG",
          "MA",
          "DZ",
          "TN",
          "LB",
          "JO",
          "PS",
          "IN",
          "BY",
          "KZ",
          "MD",
          "UA",
          "AL",
          "BA",
          "HR",
          "ME",
          "MK",
          "RS",
          "SI",
          "KR",
          "BD",
          "PK",
          "LK",
          "GH",
          "KE",
          "NG",
          "TZ",
          "UG",
          "AG",
          "AM",
          "BS",
          "BB",
          "BZ",
          "BT",
          "BW",
          "BF",
          "CV",
          "CW",
          "DM",
          "FJ",
          "GM",
          "GE",
          "GD",
          "GW",
          "GY",
          "HT",
          "JM",
          "KI",
          "LS",
          "LR",
          "MW",
          "MV",
          "ML",
          "MH",
          "FM",
          "NA",
          "NR",
          "NE",
          "PW",
          "PG",
          "PR",
          "WS",
          "SM",
          "ST",
          "SN",
          "SC",
          "SL",
          "SB",
          "KN",
          "LC",
          "VC",
          "SR",
          "TL",
          "TO",
          "TT",
          "TV",
          "VU",
          "AZ",
          "BN",
          "BI",
          "KH",
          "CM",
          "TD",
          "KM",
          "GQ",
          "SZ",
          "GA",
          "GN",
          "KG",
          "LA",
          "MO",
          "MR",
          "MN",
          "NP",
          "RW",
          "TG",
          "UZ",
          "ZW",
          "BJ",
          "MG",
          "MU",
          "MZ",
          "AO",
          "CI",
          "DJ",
          "ZM",
          "CD",
          "CG",
          "IQ",
          "LY",
          "TJ",
          "VE",
          "ET",
          "XK"
        ],
        "external_urls": {
          "spotify": "https://open.spotify.com/album/21b4cDNse2AMpj94ykfuON"
        },
        "href": "https://api.spotify.com/v1/albums/21b4cDNse2AMpj94ykfuON",
        "id": "21b4cDNse2AMpj94ykfuON",
        "images": [
          {
            "height": 640,
            "url": "https://i.scdn.co/image/ab67616d0000b273ab0d83b752dcf9f2a7ddd51b",
            "width": 640
          },
          {
            "height": 300,
            "url": "https://i.scdn.co/image/ab67616d00001e02ab0d83b752dcf9f2a7ddd51b",
            "width": 300
          },
          {
            "height": 64,
            "url": "https://i.scdn.co/image/ab67616d00004851ab0d83b752dcf9f2a7ddd51b",
            "width": 64
          }
        ],
        "is_playable": true,
        "name": "Revengeseekerz",
        "release_date": "2025-04-04",
        "release_date_precision": "day",
        "total_tracks": 12,
        "type": "album",
        "uri": "spotify:album:21b4cDNse2AMpj94ykfuON"
      },
      "artists": [
        {
          "external_urls": {
            "spotify": "https://open.spotify.com/artist/2rLGlNI6htigNxx172qxLu"
          },
          "href": "https://api.spotify.com/v1/artists/2rLGlNI6htigNxx172qxLu",
          "id": "2rLGlNI6htigNxx172qxLu",
          "name": "Jane Remover",
          "type": "artist",
          "uri": "spotify:artist:2rLGlNI6htigNxx172qxLu"
        }
      ],
      "available_markets": [
        "AR",
        "AU",
        "AT",
        "BE",
        "BO",
        "BR",
        "BG",
        "CA",
        "CL",
        "CO",
        "CR",
        "CY",
        "CZ",
        "DK",
        "DO",
        "DE",
        "EC",
        "EE",
        "SV",
        "FI",
        "FR",
        "GR",
        "GT",
        "HN",
        "HK",
        "HU",
        "IS",
        "IE",
        "IT",
        "LV",
        "LT",
        "LU",
        "MY",
        "MT",
        "MX",
        "NL",
        "NZ",
        "NI",
        "NO",
        "PA",
        "PY",
        "PE",
        "PH",
        "PL",
        "PT",
        "SG",
        "SK",
        "ES",
        "SE",
        "CH",
        "TW",
        "TR",
        "UY",
        "US",
        "GB",
        "AD",
        "LI",
        "MC",
        "ID",
        "JP",
        "TH",
        "VN",
        "RO",
        "IL",
        "ZA",
        "SA",
        "AE",
        "BH",
        "QA",
        "OM",
        "KW",
        "EG",
        "MA",
        "DZ",
        "TN",
        "LB",
        "JO",
        "PS",
        "IN",
        "BY",
        "KZ",
        "MD",
        "UA",
        "AL",
        "BA",
        "HR",
        "ME",
        "MK",
        "RS",
        "SI",
        "KR",
        "BD",
        "PK",
        "LK",
        "GH",
        "KE",
        "NG",
        "TZ",
        "UG",
        "AG",
        "AM",
        "BS",
        "BB",
        "BZ",
        "BT",
        "BW",
        "BF",
        "CV",
        "CW",
        "DM",
        "FJ",
        "GM",
        "GE",
        "GD",
        "GW",
        "GY",
        "HT",
        "JM",
        "KI",
        "LS",
        "LR",
        "MW",
        "MV",
        "ML",
        "MH",
        "FM",
        "NA",
        "NR",
        "NE",
        "PW",
        "PG",
        "PR",
        "WS",
        "SM",
        "ST",
        "SN",
        "SC",
        "SL",
        "SB",
        "KN",
        "LC",
        "VC",
        "SR",
        "TL",
        "TO",
        "TT",
        "TV",
        "VU",
        "AZ",
        "BN",
        "BI",
        "KH",
        "CM",
        "TD",
        "KM",
        "GQ",
        "SZ",
        "GA",
        "GN",
        "KG",
        "LA",
        "MO",
        "MR",
        "MN",
        "NP",
        "RW",
        "TG",
        "UZ",
        "ZW",
        "BJ",
        "MG",
        "MU",
        "MZ",
        "AO",
        "CI",
        "DJ",
        "ZM",
        "CD",
        "CG",
        "IQ",
        "LY",
        "TJ",
        "VE",
        "ET",
        "XK"
      ],
      "disc_number": 1,
      "duration_ms": 224486,
      "explicit": true,
      "external_ids": {
        "isrc": "QM24S2501673"
      },
      "external_urls": {
        "spotify": "https://open.spotify.com/track/75Wgg4LerPD3mVO5hEyUN9"
      },
      "href": "https://api.spotify.com/v1/tracks/75Wgg4LerPD3mVO5hEyUN9",
      "id": "75Wgg4LerPD3mVO5hEyUN9",
      "is_local": false,
      "is_playable": true,
      "name": "Dreamflasher",
      "popularity": 58,
      "preview_url": null,
      "track_number": 6,
      "type": "track",
      "uri": "spotify:track:75Wgg4LerPD3mVO5hEyUN9"
    },
    {
      "album": {
        "album_type": "single",
        "artists": [
          {
            "external_urls": {
              "spotify": "https://open.spotify.com/artist/3YQKmKGau1PzlVlkL1iodx"
            },
            "href": "https://api.spotify.com/v1/artists/3YQKmKGau1PzlVlkL1iodx",
            "id": "3YQKmKGau1PzlVlkL1iodx",
            "name": "Twenty One Pilots",
            "type": "artist",
            "uri": "spotify:artist:3YQKmKGau1PzlVlkL1iodx"
          }
        ],
        "available_markets": [
          "AR",
          "AU",
          "AT",
          "BE",
          "BO",
          "BR",
          "BG",
          "CA",
          "CL",
          "CO",
          "CR",
          "CY",
          "CZ",
          "DK",
          "DO",
          "DE",
          "EC",
          "EE",
          "SV",
          "FI",
          "FR",
          "GR",
          "GT",
          "HN",
          "HK",
          "HU",
          "IS",
          "IE",
          "IT",
          "LV",
          "LT",
          "LU",
          "MY",
          "MT",
          "MX",
          "NL",
          "NZ",
          "NI",
          "NO",
          "PA",
          "PY",
          "PE",
          "PH",
          "PL",
          "PT",
          "SG",
          "SK",
          "ES",
          "SE",
          "CH",
          "TW",
          "TR",
          "UY",
          "US",
          "GB",
          "AD",
          "LI",
          "MC",
          "ID",
          "JP",
          "TH",
          "VN",
          "RO",
          "IL",
          "ZA",
          "SA",
          "AE",
          "BH",
          "QA",
          "OM",
          "KW",
          "EG",
          "MA",
          "DZ",
          "TN",
          "LB",
          "JO",
          "PS",
          "IN",
          "KZ",
          "MD",
          "UA",
          "AL",
          "BA",
          "HR",
          "ME",
          "MK",
          "RS",
          "SI",
          "KR",
          "BD",
          "PK",
          "LK",
          "GH",
          "KE",
          "NG",
          "TZ",
          "UG",
          "AG",
          "AM",
          "BS",
          "BB",
          "BZ",
          "BT",
          "BW",
          "BF",
          "CV",
          "CW",
          "DM",
          "FJ",
          "GM",
          "GE",
          "GD",
          "GW",
          "GY",
          "HT",
          "JM",
          "KI",
          "LS",
          "LR",
          "MW",
          "MV",
          "ML",
          "MH",
          "FM",
          "NA",
          "NR",
          "NE",
          "PW",
          "PG",
          "PR",
          "WS",
          "SM",
          "ST",
          "SN",
          "SC",
          "SL",
          "SB",
          "KN",
          "LC",
          "VC",
          "SR",
          "TL",
          "TO",
          "TT",
          "TV",
          "VU",
          "AZ",
          "BN",
          "BI",
          "KH",
          "CM",
          "TD",
          "KM",
          "GQ",
          "SZ",
          "GA",
          "GN",
          "KG",
          "LA",
          "MO",
          "MR",
          "MN",
          "NP",
          "RW",
          "TG",
          "UZ",
          "ZW",
          "BJ",
          "MG",
          "MU",
          "MZ",
          "AO",
          "CI",
          "DJ",
          "ZM",
          "CD",
          "CG",
          "IQ",
          "LY",
          "TJ",
          "VE",
          "ET",
          "XK"
        ],
        "external_urls": {
          "spotify": "https://open.spotify.com/album/2VHIo87YnEergnRfHnQN3J"
        },
        "href": "https://api.spotify.com/v1/albums/2VHIo87YnEergnRfHnQN3J",
        "id": "2VHIo87YnEergnRfHnQN3J",
        "images": [
          {
            "height": 640,
            "url": "https://i.scdn.co/image/ab67616d0000b273546ee31f03998f0f8d497eb4",
            "width": 640
          },
          {
            "height": 300,
            "url": "https://i.scdn.co/image/ab67616d00001e02546ee31f03998f0f8d497eb4",
            "width": 300
          },
          {
            "height": 64,
            "url": "https://i.scdn.co/image/ab67616d00004851546ee31f03998f0f8d497eb4",
            "width": 64
          }
        ],
        "is_playable": true,
        "name": "The Contract",
        "release_date": "2025-06-12",
        "release_date_precision": "day",
        "total_tracks": 1,
        "type": "album",
        "uri": "spotify:album:2VHIo87YnEergnRfHnQN3J"
      },
      "artists": [
        {
          "external_urls": {
            "spotify": "https://open.spotify.com/artist/3YQKmKGau1PzlVlkL1iodx"
          },
          "href": "https://api.spotify.com/v1/artists/3YQKmKGau1PzlVlkL1iodx",
          "id": "3YQKmKGau1PzlVlkL1iodx",
          "name": "Twenty One Pilots",
          "type": "artist",
          "uri": "spotify:artist:3YQKmKGau1PzlVlkL1iodx"
        }
      ],
      "available_markets": [
        "AR",
        "AU",
        "AT",
        "BE",
        "BO",
        "BR",
        "BG",
        "CA",
        "CL",
        "CO",
        "CR",
        "CY",
        "CZ",
        "DK",
        "DO",
        "DE",
        "EC",
        "EE",
        "SV",
        "FI",
        "FR",
        "GR",
        "GT",
        "HN",
        "HK",
        "HU",
        "IS",
        "IE",
        "IT",
        "LV",
        "LT",
        "LU",
        "MY",
        "MT",
        "MX",
        "NL",
        "NZ",
        "NI",
        "NO",
        "PA",
        "PY",
        "PE",
        "PH",
        "PL",
        "PT",
        "SG",
        "SK",
        "ES",
        "SE",
        "CH",
        "TW",
        "TR",
        "UY",
        "US",
        "GB",
        "AD",
        "LI",
        "MC",
        "ID",
        "JP",
        "TH",
        "VN",
        "RO",
        "IL",
        "ZA",
        "SA",
        "AE",
        "BH",
        "QA",
        "OM",
        "KW",
        "EG",
        "MA",
        "DZ",
        "TN",
        "LB",
        "JO",
        "PS",
        "IN",
        "KZ",
        "MD",
        "UA",
        "AL",
        "BA",
        "HR",
        "ME",
        "MK",
        "RS",
        "SI",
        "KR",
        "BD",
        "PK",
        "LK",
        "GH",
        "KE",
        "NG",
        "TZ",
        "UG",
        "AG",
        "AM",
        "BS",
        "BB",
        "BZ",
        "BT",
        "BW",
        "BF",
        "CV",
        "CW",
        "DM",
        "FJ",
        "GM",
        "GE",
        "GD",
        "GW",
        "GY",
        "HT",
        "JM",
        "KI",
        "LS",
        "LR",
        "MW",
        "MV",
        "ML",
        "MH",
        "FM",
        "NA",
        "NR",
        "NE",
        "PW",
        "PG",
        "PR",
        "WS",
        "SM",
        "ST",
        "SN",
        "SC",
        "SL",
        "SB",
        "KN",
        "LC",
        "VC",
        "SR",
        "TL",
        "TO",
        "TT",
        "TV",
        "VU",
        "AZ",
        "BN",
        "BI",
        "KH",
        "CM",
        "TD",
        "KM",
        "GQ",
        "SZ",
        "GA",
        "GN",
        "KG",
        "LA",
        "MO",
        "MR",
        "MN",
        "NP",
        "RW",
        "TG",
        "UZ",
        "ZW",
        "BJ",
        "MG",
        "MU",
        "MZ",
        "AO",
        "CI",
        "DJ",
        "ZM",
        "CD",
        "CG",
        "IQ",
        "LY",
        "TJ",
        "VE",
        "ET",
        "XK"
      ],
      "disc_number": 1,
      "duration_ms": 228000,
      "explicit": false,
      "external_ids": {
        "isrc": "USAT22503458"
      },
      "external_urls": {
        "spotify": "https://open.spotify.com/track/6DzXaIgVIH7oLA1pkUtFaG"
      },
      "href": "https://api.spotify.com/v1/tracks/6DzXaIgVIH7oLA1pkUtFaG",
      "id": "6DzXaIgVIH7oLA1pkUtFaG",
      "is_local": false,
      "is_playable": true,
      "name": "The Contract",
      "popularity": 83,
      "preview_url": null,
      "track_number": 1,
      "type": "track",
      "uri": "spotify:track:6DzXaIgVIH7oLA1pkUtFaG"
    },
    {
      "album": {
        "album_type": "album",
        "artists": [
          {
            "external_urls": {
              "spotify": "https://open.spotify.com/artist/2rLGlNI6htigNxx172qxLu"
            },
            "href": "https://api.spotify.com/v1/artists/2rLGlNI6htigNxx172qxLu",
            "id": "2rLGlNI6htigNxx172qxLu",
            "name": "Jane Remover",
            "type": "artist",
            "uri": "spotify:artist:2rLGlNI6htigNxx172qxLu"
          }
        ],
        "available_markets": [
          "AR",
          "AU",
          "AT",
          "BE",
          "BO",
          "BR",
          "BG",
          "CA",
          "CL",
          "CO",
          "CR",
          "CY",
          "CZ",
          "DK",
          "DO",
          "DE",
          "EC",
          "EE",
          "SV",
          "FI",
          "FR",
          "GR",
          "GT",
          "HN",
          "HK",
          "HU",
          "IS",
          "IE",
          "IT",
          "LV",
          "LT",
          "LU",
          "MY",
          "MT",
          "MX",
          "NL",
          "NZ",
          "NI",
          "NO",
          "PA",
          "PY",
          "PE",
          "PH",
          "PL",
          "PT",
          "SG",
          "SK",
          "ES",
          "SE",
          "CH",
          "TW",
          "TR",
          "UY",
          "US",
          "GB",
          "AD",
          "LI",
          "MC",
          "ID",
          "JP",
          "TH",
          "VN",
          "RO",
          "IL",
          "ZA",
          "SA",
          "AE",
          "BH",
          "QA",
          "OM",
          "KW",
          "EG",
          "MA",
          "DZ",
          "TN",
          "LB",
          "JO",
          "PS",
          "IN",
          "BY",
          "KZ",
          "MD",
          "UA",
          "AL",
          "BA",
          "HR",
          "ME",
          "MK",
          "RS",
          "SI",
          "KR",
          "BD",
          "PK",
          "LK",
          "GH",
          "KE",
          "NG",
          "TZ",
          "UG",
          "AG",
          "AM",
          "BS",
          "BB",
          "BZ",
          "BT",
          "BW",
          "BF",
          "CV",
          "CW",
          "DM",
          "FJ",
          "GM",
          "GE",
          "GD",
          "GW",
          "GY",
          "HT",
          "JM",
          "KI",
          "LS",
          "LR",
          "MW",
          "MV",
          "ML",
          "MH",
          "FM",
          "NA",
          "NR",
          "NE",
          "PW",
          "PG",
          "PR",
          "WS",
          "SM",
          "ST",
          "SN",
          "SC",
          "SL",
          "SB",
          "KN",
          "LC",
          "VC",
          "SR",
          "TL",
          "TO",
          "TT",
          "TV",
          "VU",
          "AZ",
          "BN",
          "BI",
          "KH",
          "CM",
          "TD",
          "KM",
          "GQ",
          "SZ",
          "GA",
          "GN",
          "KG",
          "LA",
          "MO",
          "MR",
          "MN",
          "NP",
          "RW",
          "TG",
          "UZ",
          "ZW",
          "BJ",
          "MG",
          "MU",
          "MZ",
          "AO",
          "CI",
          "DJ",
          "ZM",
          "CD",
          "CG",
          "IQ",
          "LY",
          "TJ",
          "VE",
          "ET",
          "XK"
        ],
        "external_urls": {
          "spotify": "https://open.spotify.com/album/0Pm3i5huHlt1mjSLxyA1Re"
        },
        "href": "https://api.spotify.com/v1/albums/0Pm3i5huHlt1mjSLxyA1Re",
        "id": "0Pm3i5huHlt1mjSLxyA1Re",
        "images": [
          {
            "height": 640,
            "url": "https://i.scdn.co/image/ab67616d0000b2732f5066ea2ce297e83fe6c724",
            "width": 640
          },
          {
            "height": 300,
            "url": "https://i.scdn.co/image/ab67616d00001e022f5066ea2ce297e83fe6c724",
            "width": 300
          },
          {
            "height": 64,
            "url": "https://i.scdn.co/image/ab67616d000048512f5066ea2ce297e83fe6c724",
            "width": 64
          }
        ],
        "is_playable": true,
        "name": "Frailty",
        "release_date": "2021-11-12",
        "release_date_precision": "day",
        "total_tracks": 13,
        "type": "album",
        "uri": "spotify:album:0Pm3i5huHlt1mjSLxyA1Re"
      },
      "artists": [
        {
          "external_urls": {
            "spotify": "https://open.spotify.com/artist/2rLGlNI6htigNxx172qxLu"
          },
          "href": "https://api.spotify.com/v1/artists/2rLGlNI6htigNxx172qxLu",
          "id": "2rLGlNI6htigNxx172qxLu",
          "name": "Jane Remover",
          "type": "artist",
          "uri": "spotify:artist:2rLGlNI6htigNxx172qxLu"
        }
      ],
      "available_markets": [
        "AR",
        "AU",
        "AT",
        "BE",
        "BO",
        "BR",
        "BG",
        "CA",
        "CL",
        "CO",
        "CR",
        "CY",
        "CZ",
        "DK",
        "DO",
        "DE",
        "EC",
        "EE",
        "SV",
        "FI",
        "FR",
        "GR",
        "GT",
        "HN",
        "HK",
        "HU",
        "IS",
        "IE",
        "IT",
        "LV",
        "LT",
        "LU",
        "MY",
        "MT",
        "MX",
        "NL",
        "NZ",
        "NI",
        "NO",
        "PA",
        "PY",
        "PE",
        "PH",
        "PL",
        "PT",
        "SG",
        "SK",
        "ES",
        "SE",
        "CH",
        "TW",
        "TR",
        "UY",
        "US",
        "GB",
        "AD",
        "LI",
        "MC",
        "ID",
        "JP",
        "TH",
        "VN",
        "RO",
        "IL",
        "ZA",
        "SA",
        "AE",
        "BH",
        "QA",
        "OM",
        "KW",
        "EG",
        "MA",
        "DZ",
        "TN",
        "LB",
        "JO",
        "PS",
        "IN",
        "BY",
        "KZ",
        "MD",
        "UA",
        "AL",
        "BA",
        "HR",
        "ME",
        "MK",
        "RS",
        "SI",
        "KR",
        "BD",
        "PK",
        "LK",
        "GH",
        "KE",
        "NG",
        "TZ",
        "UG",
        "AG",
        "AM",
        "BS",
        "BB",
        "BZ",
        "BT",
        "BW",
        "BF",
        "CV",
        "CW",
        "DM",
        "FJ",
        "GM",
        "GE",
        "GD",
        "GW",
        "GY",
        "HT",
        "JM",
        "KI",
        "LS",
        "LR",
        "MW",
        "MV",
        "ML",
        "MH",
        "FM",
        "NA",
        "NR",
        "NE",
        "PW",
        "PG",
        "PR",
        "WS",
        "SM",
        "ST",
        "SN",
        "SC",
        "SL",
        "SB",
        "KN",
        "LC",
        "VC",
        "SR",
        "TL",
        "TO",
        "TT",
        "TV",
        "VU",
        "AZ",
        "BN",
        "BI",
        "KH",
        "CM",
        "TD",
        "KM",
        "GQ",
        "SZ",
        "GA",
        "GN",
        "KG",
        "LA",
        "MO",
        "MR",
        "MN",
        "NP",
        "RW",
        "TG",
        "UZ",
        "ZW",
        "BJ",
        "MG",
        "MU",
        "MZ",
        "AO",
        "CI",
        "DJ",
        "ZM",
        "CD",
        "CG",
        "IQ",
        "LY",
        "TJ",
        "VE",
        "ET",
        "XK"
      ],
      "disc_number": 1,
      "duration_ms": 345796,
      "explicit": false,
      "external_ids": {
        "isrc": "QZH5E2130662"
      },
      "external_urls": {
        "spotify": "https://open.spotify.com/track/30YaPM8Aba7TVcyaiZFbWC"
      },
      "href": "https://api.spotify.com/v1/tracks/30YaPM8Aba7TVcyaiZFbWC",
      "id": "30YaPM8Aba7TVcyaiZFbWC",
      "is_local": false,
      "is_playable": true,
      "name": "movies for guys",
      "popularity": 51,
      "preview_url": null,
      "track_number": 7,
      "type": "track",
      "uri": "spotify:track:30YaPM8Aba7TVcyaiZFbWC"
    },
    {
      "album": {
        "album_type": "album",
        "artists": [
          {
            "external_urls": {
              "spotify": "https://open.spotify.com/artist/25uiPmTg16RbhZWAqwLBy5"
            },
            "href": "https://api.spotify.com/v1/artists/25uiPmTg16RbhZWAqwLBy5",
            "id": "25uiPmTg16RbhZWAqwLBy5",
            "name": "Charli xcx",
            "type": "artist",
            "uri": "spotify:artist:25uiPmTg16RbhZWAqwLBy5"
          }
        ],
        "available_markets": [
          "AR",
          "AU",
          "AT",
          "BE",
          "BO",
          "BR",
          "BG",
          "CA",
          "CL",
          "CO",
          "CR",
          "CY",
          "CZ",
          "DK",
          "DO",
          "DE",
          "EC",
          "EE",
          "SV",
          "FI",
          "FR",
          "GR",
          "GT",
          "HN",
          "HK",
          "HU",
          "IS",
          "IE",
          "IT",
          "LV",
          "LT",
          "LU",
          "MY",
          "MT",
          "MX",
          "NL",
          "NZ",
          "NI",
          "NO",
          "PA",
          "PY",
          "PE",
          "PH",
          "PL",
          "PT",
          "SG",
          "SK",
          "ES",
          "SE",
          "CH",
          "TW",
          "TR",
          "UY",
          "US",
          "GB",
          "AD",
          "LI",
          "MC",
          "ID",
          "JP",
          "TH",
          "VN",
          "RO",
          "IL",
          "ZA",
          "SA",
          "AE",
          "BH",
          "QA",
          "OM",
          "KW",
          "EG",
          "MA",
          "DZ",
          "TN",
          "LB",
          "JO",
          "PS",
          "IN",
          "BY",
          "KZ",
          "MD",
          "UA",
          "AL",
          "BA",
          "HR",
          "ME",
          "MK",
          "RS",
          "SI",
          "KR",
          "BD",
          "PK",
          "LK",
          "GH",
          "KE",
          "NG",
          "TZ",
          "UG",
          "AG",
          "AM",
          "BS",
          "BB",
          "BZ",
          "BT",
          "BW",
          "BF",
          "CV",
          "CW",
          "DM",
          "FJ",
          "GM",
          "GE",
          "GD",
          "GW",
          "GY",
          "HT",
          "JM",
          "KI",
          "LS",
          "LR",
          "MW",
          "MV",
          "ML",
          "MH",
          "FM",
          "NA",
          "NR",
          "NE",
          "PW",
          "PG",
          "PR",
          "WS",
          "SM",
          "ST",
          "SN",
          "SC",
          "SL",
          "SB",
          "KN",
          "LC",
          "VC",
          "SR",
          "TL",
          "TO",
          "TT",
          "TV",
          "VU",
          "AZ",
          "BN",
          "BI",
          "KH",
          "CM",
          "TD",
          "KM",
          "GQ",
          "SZ",
          "GA",
          "GN",
          "KG",
          "LA",
          "MO",
          "MR",
          "MN",
          "NP",
          "RW",
          "TG",
          "UZ",
          "ZW",
          "BJ",
          "MG",
          "MU",
          "MZ",
          "AO",
          "CI",
          "DJ",
          "ZM",
          "CD",
          "CG",
          "IQ",
          "LY",
          "TJ",
          "VE",
          "ET",
          "XK"
        ],
        "external_urls": {
          "spotify": "https://open.spotify.com/album/3a9qH2VEsSiOZvMrjaS0Nu"
        },
        "href": "https://api.spotify.com/v1/albums/3a9qH2VEsSiOZvMrjaS0Nu",
        "id": "3a9qH2VEsSiOZvMrjaS0Nu",
        "images": [
          {
            "height": 640,
            "url": "https://i.scdn.co/image/ab67616d0000b27349bdbd5880802dcbe4e0b2dd",
            "width": 640
          },
          {
            "height": 300,
            "url": "https://i.scdn.co/image/ab67616d00001e0249bdbd5880802dcbe4e0b2dd",
            "width": 300
          },
          {
            "height": 64,
            "url": "https://i.scdn.co/image/ab67616d0000485149bdbd5880802dcbe4e0b2dd",
            "width": 64
          }
        ],
        "is_playable": true,
        "name": "how i'm feeling now",
        "release_date": "2020-05-15",
        "release_date_precision": "day",
        "total_tracks": 11,
        "type": "album",
        "uri": "spotify:album:3a9qH2VEsSiOZvMrjaS0Nu"
      },
      "artists": [
        {
          "external_urls": {
            "spotify": "https://open.spotify.com/artist/25uiPmTg16RbhZWAqwLBy5"
          },
          "href": "https://api.spotify.com/v1/artists/25uiPmTg16RbhZWAqwLBy5",
          "id": "25uiPmTg16RbhZWAqwLBy5",
          "name": "Charli xcx",
          "type": "artist",
          "uri": "spotify:artist:25uiPmTg16RbhZWAqwLBy5"
        }
      ],
      "available_markets": [
        "AR",
        "AU",
        "AT",
        "BE",
        "BO",
        "BR",
        "BG",
        "CA",
        "CL",
        "CO",
        "CR",
        "CY",
        "CZ",
        "DK",
        "DO",
        "DE",
        "EC",
        "EE",
        "SV",
        "FI",
        "FR",
        "GR",
        "GT",
        "HN",
        "HK",
        "HU",
        "IS",
        "IE",
        "IT",
        "LV",
        "LT",
        "LU",
        "MY",
        "MT",
        "MX",
        "NL",
        "NZ",
        "NI",
        "NO",
        "PA",
        "PY",
        "PE",
        "PH",
        "PL",
        "PT",
        "SG",
        "SK",
        "ES",
        "SE",
        "CH",
        "TW",
        "TR",
        "UY",
        "US",
        "GB",
        "AD",
        "LI",
        "MC",
        "ID",
        "JP",
        "TH",
        "VN",
        "RO",
        "IL",
        "ZA",
        "SA",
        "AE",
        "BH",
        "QA",
        "OM",
        "KW",
        "EG",
        "MA",
        "DZ",
        "TN",
        "LB",
        "JO",
        "PS",
        "IN",
        "BY",
        "KZ",
        "MD",
        "UA",
        "AL",
        "BA",
        "HR",
        "ME",
        "MK",
        "RS",
        "SI",
        "KR",
        "BD",
        "PK",
        "LK",
        "GH",
        "KE",
        "NG",
        "TZ",
        "UG",
        "AG",
        "AM",
        "BS",
        "BB",
        "BZ",
        "BT",
        "BW",
        "BF",
        "CV",
        "CW",
        "DM",
        "FJ",
        "GM",
        "GE",
        "GD",
        "GW",
        "GY",
        "HT",
        "JM",
        "KI",
        "LS",
        "LR",
        "MW",
        "MV",
        "ML",
        "MH",
        "FM",
        "NA",
        "NR",
        "NE",
        "PW",
        "PG",
        "PR",
        "WS",
        "SM",
        "ST",
        "SN",
        "SC",
        "SL",
        "SB",
        "KN",
        "LC",
        "VC",
        "SR",
        "TL",
        "TO",
        "TT",
        "TV",
        "VU",
        "AZ",
        "BN",
        "BI",
        "KH",
        "CM",
        "TD",
        "KM",
        "GQ",
        "SZ",
        "GA",
        "GN",
        "KG",
        "LA",
        "MO",
        "MR",
        "MN",
        "NP",
        "RW",
        "TG",
        "UZ",
        "ZW",
        "BJ",
        "MG",
        "MU",
        "MZ",
        "AO",
        "CI",
        "DJ",
        "ZM",
        "CD",
        "CG",
        "IQ",
        "LY",
        "TJ",
        "VE",
        "ET",
        "XK"
      ],
      "disc_number": 1,
      "duration_ms": 149390,
      "explicit": false,
      "external_ids": {
        "isrc": "GBAHS2000212"
      },
      "external_urls": {
        "spotify": "https://open.spotify.com/track/7Dexi5Z2IowCkHrnzlWysc"
      },
      "href": "https://api.spotify.com/v1/tracks/7Dexi5Z2IowCkHrnzlWysc",
      "id": "7Dexi5Z2IowCkHrnzlWysc",
      "is_local": false,
      "is_playable": true,
      "name": "claws",
      "popularity": 69,
      "preview_url": null,
      "track_number": 3,
      "type": "track",
      "uri": "spotify:track:7Dexi5Z2IowCkHrnzlWysc"
    },
    {
      "album": {
        "album_type": "album",
        "artists": [
          {
            "external_urls": {
              "spotify": "https://open.spotify.com/artist/2rLGlNI6htigNxx172qxLu"
            },
            "href": "https://api.spotify.com/v1/artists/2rLGlNI6htigNxx172qxLu",
            "id": "2rLGlNI6htigNxx172qxLu",
            "name": "Jane Remover",
            "type": "artist",
            "uri": "spotify:artist:2rLGlNI6htigNxx172qxLu"
          }
        ],
        "available_markets": [
          "AR",
          "AU",
          "AT",
          "BE",
          "BO",
          "BR",
          "BG",
          "CA",
          "CL",
          "CO",
          "CR",
          "CY",
          "CZ",
          "DK",
          "DO",
          "DE",
          "EC",
          "EE",
          "SV",
          "FI",
          "FR",
          "GR",
          "GT",
          "HN",
          "HK",
          "HU",
          "IS",
          "IE",
          "IT",
          "LV",
          "LT",
          "LU",
          "MY",
          "MT",
          "MX",
          "NL",
          "NZ",
          "NI",
          "NO",
          "PA",
          "PY",
          "PE",
          "PH",
          "PL",
          "PT",
          "SG",
          "SK",
          "ES",
          "SE",
          "CH",
          "TW",
          "TR",
          "UY",
          "US",
          "GB",
          "AD",
          "LI",
          "MC",
          "ID",
          "JP",
          "TH",
          "VN",
          "RO",
          "IL",
          "ZA",
          "SA",
          "AE",
          "BH",
          "QA",
          "OM",
          "KW",
          "EG",
          "MA",
          "DZ",
          "TN",
          "LB",
          "JO",
          "PS",
          "IN",
          "BY",
          "KZ",
          "MD",
          "UA",
          "AL",
          "BA",
          "HR",
          "ME",
          "MK",
          "RS",
          "SI",
          "KR",
          "BD",
          "PK",
          "LK",
          "GH",
          "KE",
          "NG",
          "TZ",
          "UG",
          "AG",
          "AM",
          "BS",
          "BB",
          "BZ",
          "BT",
          "BW",
          "BF",
          "CV",
          "CW",
          "DM",
          "FJ",
          "GM",
          "GE",
          "GD",
          "GW",
          "GY",
          "HT",
          "JM",
          "KI",
          "LS",
          "LR",
          "MW",
          "MV",
          "ML",
          "MH",
          "FM",
          "NA",
          "NR",
          "NE",
          "PW",
          "PG",
          "PR",
          "WS",
          "SM",
          "ST",
          "SN",
          "SC",
          "SL",
          "SB",
          "KN",
          "LC",
          "VC",
          "SR",
          "TL",
          "TO",
          "TT",
          "TV",
          "VU",
          "AZ",
          "BN",
          "BI",
          "KH",
          "CM",
          "TD",
          "KM",
          "GQ",
          "SZ",
          "GA",
          "GN",
          "KG",
          "LA",
          "MO",
          "MR",
          "MN",
          "NP",
          "RW",
          "TG",
          "UZ",
          "ZW",
          "BJ",
          "MG",
          "MU",
          "MZ",
          "AO",
          "CI",
          "DJ",
          "ZM",
          "CD",
          "CG",
          "IQ",
          "LY",
          "TJ",
          "VE",
          "ET",
          "XK"
        ],
        "external_urls": {
          "spotify": "https://open.spotify.com/album/21b4cDNse2AMpj94ykfuON"
        },
        "href": "https://api.spotify.com/v1/albums/21b4cDNse2AMpj94ykfuON",
        "id": "21b4cDNse2AMpj94ykfuON",
        "images": [
          {
            "height": 640,
            "url": "https://i.scdn.co/image/ab67616d0000b273ab0d83b752dcf9f2a7ddd51b",
            "width": 640
          },
          {
            "height": 300,
            "url": "https://i.scdn.co/image/ab67616d00001e02ab0d83b752dcf9f2a7ddd51b",
            "width": 300
          },
          {
            "height": 64,
            "url": "https://i.scdn.co/image/ab67616d00004851ab0d83b752dcf9f2a7ddd51b",
            "width": 64
          }
        ],
        "is_playable": true,
        "name": "Revengeseekerz",
        "release_date": "2025-04-04",
        "release_date_precision": "day",
        "total_tracks": 12,
        "type": "album",
        "uri": "spotify:album:21b4cDNse2AMpj94ykfuON"
      },
      "artists": [
        {
          "external_urls": {
            "spotify": "https://open.spotify.com/artist/2rLGlNI6htigNxx172qxLu"
          },
          "href": "https://api.spotify.com/v1/artists/2rLGlNI6htigNxx172qxLu",
          "id": "2rLGlNI6htigNxx172qxLu",
          "name": "Jane Remover",
          "type": "artist",
          "uri": "spotify:artist:2rLGlNI6htigNxx172qxLu"
        }
      ],
      "available_markets": [
        "AR",
        "AU",
        "AT",
        "BE",
        "BO",
        "BR",
        "BG",
        "CA",
        "CL",
        "CO",
        "CR",
        "CY",
        "CZ",
        "DK",
        "DO",
        "DE",
        "EC",
        "EE",
        "SV",
        "FI",
        "FR",
        "GR",
        "GT",
        "HN",
        "HK",
        "HU",
        "IS",
        "IE",
        "IT",
        "LV",
        "LT",
        "LU",
        "MY",
        "MT",
        "MX",
        "NL",
        "NZ",
        "NI",
        "NO",
        "PA",
        "PY",
        "PE",
        "PH",
        "PL",
        "PT",
        "SG",
        "SK",
        "ES",
        "SE",
        "CH",
        "TW",
        "TR",
        "UY",
        "US",
        "GB",
        "AD",
        "LI",
        "MC",
        "ID",
        "JP",
        "TH",
        "VN",
        "RO",
        "IL",
        "ZA",
        "SA",
        "AE",
        "BH",
        "QA",
        "OM",
        "KW",
        "EG",
        "MA",
        "DZ",
        "TN",
        "LB",
        "JO",
        "PS",
        "IN",
        "BY",
        "KZ",
        "MD",
        "UA",
        "AL",
        "BA",
        "HR",
        "ME",
        "MK",
        "RS",
        "SI",
        "KR",
        "BD",
        "PK",
        "LK",
        "GH",
        "KE",
        "NG",
        "TZ",
        "UG",
        "AG",
        "AM",
        "BS",
        "BB",
        "BZ",
        "BT",
        "BW",
        "BF",
        "CV",
        "CW",
        "DM",
        "FJ",
        "GM",
        "GE",
        "GD",
        "GW",
        "GY",
        "HT",
        "JM",
        "KI",
        "LS",
        "LR",
        "MW",
        "MV",
        "ML",
        "MH",
        "FM",
        "NA",
        "NR",
        "NE",
        "PW",
        "PG",
        "PR",
        "WS",
        "SM",
        "ST",
        "SN",
        "SC",
        "SL",
        "SB",
        "KN",
        "LC",
        "VC",
        "SR",
        "TL",
        "TO",
        "TT",
        "TV",
        "VU",
        "AZ",
        "BN",
        "BI",
        "KH",
        "CM",
        "TD",
        "KM",
        "GQ",
        "SZ",
        "GA",
        "GN",
        "KG",
        "LA",
        "MO",
        "MR",
        "MN",
        "NP",
        "RW",
        "TG",
        "UZ",
        "ZW",
        "BJ",
        "MG",
        "MU",
        "MZ",
        "AO",
        "CI",
        "DJ",
        "ZM",
        "CD",
        "CG",
        "IQ",
        "LY",
        "TJ",
        "VE",
        "ET",
        "XK"
      ],
      "disc_number": 1,
      "duration_ms": 200571,
      "explicit": true,
      "external_ids": {
        "isrc": "QM24S2501671"
      },
      "external_urls": {
        "spotify": "https://open.spotify.com/track/5XNf2R7PzOkaBKeaBUREJS"
      },
      "href": "https://api.spotify.com/v1/tracks/5XNf2R7PzOkaBKeaBUREJS",
      "id": "5XNf2R7PzOkaBKeaBUREJS",
      "is_local": false,
      "is_playable": true,
      "name": "Fadeoutz",
      "popularity": 52,
      "preview_url": null,
      "track_number": 9,
      "type": "track",
      "uri": "spotify:track:5XNf2R7PzOkaBKeaBUREJS"
    },
    {
      "album": {
        "album_type": "album",
        "artists": [
          {
            "external_urls": {
              "spotify": "https://open.spotify.com/artist/3Vl9fyKMIdLMswk8ai3mm9"
            },
            "href": "https://api.spotify.com/v1/artists/3Vl9fyKMIdLMswk8ai3mm9",
            "id": "3Vl9fyKMIdLMswk8ai3mm9",
            "name": "Rebecca Black",
            "type": "artist",
            "uri": "spotify:artist:3Vl9fyKMIdLMswk8ai3mm9"
          }
        ],
        "available_markets": [
          "AR",
          "AU",
          "AT",
          "BE",
          "BO",
          "BR",
          "BG",
          "CA",
          "CL",
          "CO",
          "CR",
          "CY",
          "CZ",
          "DK",
          "DO",
          "DE",
          "EC",
          "EE",
          "SV",
          "FI",
          "FR",
          "GR",
          "GT",
          "HN",
          "HK",
          "HU",
          "IS",
          "IE",
          "IT",
          "LV",
          "LT",
          "LU",
          "MY",
          "MT",
          "MX",
          "NL",
          "NZ",
          "NI",
          "NO",
          "PA",
          "PY",
          "PE",
          "PH",
          "PL",
          "PT",
          "SG",
          "SK",
          "ES",
          "SE",
          "CH",
          "TW",
          "TR",
          "UY",
          "US",
          "GB",
          "AD",
          "LI",
          "MC",
          "ID",
          "JP",
          "TH",
          "VN",
          "RO",
          "IL",
          "ZA",
          "SA",
          "AE",
          "BH",
          "QA",
          "OM",
          "KW",
          "EG",
          "MA",
          "DZ",
          "TN",
          "LB",
          "JO",
          "PS",
          "IN",
          "BY",
          "KZ",
          "MD",
          "UA",
          "AL",
          "BA",
          "HR",
          "ME",
          "MK",
          "RS",
          "SI",
          "KR",
          "BD",
          "PK",
          "LK",
          "GH",
          "KE",
          "NG",
          "TZ",
          "UG",
          "AG",
          "AM",
          "BS",
          "BB",
          "BZ",
          "BT",
          "BW",
          "BF",
          "CV",
          "CW",
          "DM",
          "FJ",
          "GM",
          "GE",
          "GD",
          "GW",
          "GY",
          "HT",
          "JM",
          "KI",
          "LS",
          "LR",
          "MW",
          "MV",
          "ML",
          "MH",
          "FM",
          "NA",
          "NR",
          "NE",
          "PW",
          "PG",
          "PR",
          "WS",
          "SM",
          "ST",
          "SN",
          "SC",
          "SL",
          "SB",
          "KN",
          "LC",
          "VC",
          "SR",
          "TL",
          "TO",
          "TT",
          "TV",
          "VU",
          "AZ",
          "BN",
          "BI",
          "KH",
          "CM",
          "TD",
          "KM",
          "GQ",
          "SZ",
          "GA",
          "GN",
          "KG",
          "LA",
          "MO",
          "MR",
          "MN",
          "NP",
          "RW",
          "TG",
          "UZ",
          "ZW",
          "BJ",
          "MG",
          "MU",
          "MZ",
          "AO",
          "CI",
          "DJ",
          "ZM",
          "CD",
          "CG",
          "IQ",
          "LY",
          "TJ",
          "VE",
          "ET",
          "XK"
        ],
        "external_urls": {
          "spotify": "https://open.spotify.com/album/7ejtUeGJ9QV8IQHEBRGRWr"
        },
        "href": "https://api.spotify.com/v1/albums/7ejtUeGJ9QV8IQHEBRGRWr",
        "id": "7ejtUeGJ9QV8IQHEBRGRWr",
        "images": [
          {
            "height": 640,
            "url": "https://i.scdn.co/image/ab67616d0000b273fbc3499c5b3db0cb87376f64",
            "width": 640
          },
          {
            "height": 300,
            "url": "https://i.scdn.co/image/ab67616d00001e02fbc3499c5b3db0cb87376f64",
            "width": 300
          },
          {
            "height": 64,
            "url": "https://i.scdn.co/image/ab67616d00004851fbc3499c5b3db0cb87376f64",
            "width": 64
          }
        ],
        "is_playable": true,
        "name": "Let Her Burn",
        "release_date": "2023-02-09",
        "release_date_precision": "day",
        "total_tracks": 10,
        "type": "album",
        "uri": "spotify:album:7ejtUeGJ9QV8IQHEBRGRWr"
      },
      "artists": [
        {
          "external_urls": {
            "spotify": "https://open.spotify.com/artist/3Vl9fyKMIdLMswk8ai3mm9"
          },
          "href": "https://api.spotify.com/v1/artists/3Vl9fyKMIdLMswk8ai3mm9",
          "id": "3Vl9fyKMIdLMswk8ai3mm9",
          "name": "Rebecca Black",
          "type": "artist",
          "uri": "spotify:artist:3Vl9fyKMIdLMswk8ai3mm9"
        }
      ],
      "available_markets": [
        "AR",
        "AU",
        "AT",
        "BE",
        "BO",
        "BR",
        "BG",
        "CA",
        "CL",
        "CO",
        "CR",
        "CY",
        "CZ",
        "DK",
        "DO",
        "DE",
        "EC",
        "EE",
        "SV",
        "FI",
        "FR",
        "GR",
        "GT",
        "HN",
        "HK",
        "HU",
        "IS",
        "IE",
        "IT",
        "LV",
        "LT",
        "LU",
        "MY",
        "MT",
        "MX",
        "NL",
        "NZ",
        "NI",
        "NO",
        "PA",
        "PY",
        "PE",
        "PH",
        "PL",
        "PT",
        "SG",
        "SK",
        "ES",
        "SE",
        "CH",
        "TW",
        "TR",
        "UY",
        "US",
        "GB",
        "AD",
        "LI",
        "MC",
        "ID",
        "JP",
        "TH",
        "VN",
        "RO",
        "IL",
        "ZA",
        "SA",
        "AE",
        "BH",
        "QA",
        "OM",
        "KW",
        "EG",
        "MA",
        "DZ",
        "TN",
        "LB",
        "JO",
        "PS",
        "IN",
        "BY",
        "KZ",
        "MD",
        "UA",
        "AL",
        "BA",
        "HR",
        "ME",
        "MK",
        "RS",
        "SI",
        "KR",
        "BD",
        "PK",
        "LK",
        "GH",
        "KE",
        "NG",
        "TZ",
        "UG",
        "AG",
        "AM",
        "BS",
        "BB",
        "BZ",
        "BT",
        "BW",
        "BF",
        "CV",
        "CW",
        "DM",
        "FJ",
        "GM",
        "GE",
        "GD",
        "GW",
        "GY",
        "HT",
        "JM",
        "KI",
        "LS",
        "LR",
        "MW",
        "MV",
        "ML",
        "MH",
        "FM",
        "NA",
        "NR",
        "NE",
        "PW",
        "PG",
        "PR",
        "WS",
        "SM",
        "ST",
        "SN",
        "SC",
        "SL",
        "SB",
        "KN",
        "LC",
        "VC",
        "SR",
        "TL",
        "TO",
        "TT",
        "TV",
        "VU",
        "AZ",
        "BN",
        "BI",
        "KH",
        "CM",
        "TD",
        "KM",
        "GQ",
        "SZ",
        "GA",
        "GN",
        "KG",
        "LA",
        "MO",
        "MR",
        "MN",
        "NP",
        "RW",
        "TG",
        "UZ",
        "ZW",
        "BJ",
        "MG",
        "MU",
        "MZ",
        "AO",
        "CI",
        "DJ",
        "ZM",
        "CD",
        "CG",
        "IQ",
        "LY",
        "TJ",
        "VE",
        "ET",
        "XK"
      ],
      "disc_number": 1,
      "duration_ms": 155202,
      "explicit": true,
      "external_ids": {
        "isrc": "USANG2246654"
      },
      "external_urls": {
        "spotify": "https://open.spotify.com/track/6Egg7lLEvmFsMFA8qAqmYw"
      },
      "href": "https://api.spotify.com/v1/tracks/6Egg7lLEvmFsMFA8qAqmYw",
      "id": "6Egg7lLEvmFsMFA8qAqmYw",
      "is_local": false,
      "is_playable": true,
      "name": "Doe Eyed",
      "popularity": 37,
      "preview_url": null,
      "track_number": 5,
      "type": "track",
      "uri": "spotify:track:6Egg7lLEvmFsMFA8qAqmYw"
    },
    {
      "album": {
        "album_type": "album",
        "artists": [
          {
            "external_urls": {
              "spotify": "https://open.spotify.com/artist/5YYrWH3w4JYijU4JZrOXWA"
            },
            "href": "https://api.spotify.com/v1/artists/5YYrWH3w4JYijU4JZrOXWA",
            "id": "5YYrWH3w4JYijU4JZrOXWA",
            "name": "Rose Gray",
            "type": "artist",
            "uri": "spotify:artist:5YYrWH3w4JYijU4JZrOXWA"
          }
        ],
        "available_markets": [
          "AR",
          "AU",
          "AT",
          "BE",
          "BO",
          "BR",
          "BG",
          "CA",
          "CL",
          "CO",
          "CR",
          "CY",
          "CZ",
          "DK",
          "DO",
          "DE",
          "EC",
          "EE",
          "SV",
          "FI",
          "FR",
          "GR",
          "GT",
          "HN",
          "HK",
          "HU",
          "IS",
          "IE",
          "IT",
          "LV",
          "LT",
          "LU",
          "MY",
          "MT",
          "MX",
          "NL",
          "NZ",
          "NI",
          "NO",
          "PA",
          "PY",
          "PE",
          "PH",
          "PL",
          "PT",
          "SG",
          "SK",
          "ES",
          "SE",
          "CH",
          "TW",
          "TR",
          "UY",
          "US",
          "GB",
          "AD",
          "LI",
          "MC",
          "ID",
          "JP",
          "TH",
          "VN",
          "RO",
          "IL",
          "ZA",
          "SA",
          "AE",
          "BH",
          "QA",
          "OM",
          "KW",
          "EG",
          "MA",
          "DZ",
          "TN",
          "LB",
          "JO",
          "PS",
          "IN",
          "BY",
          "KZ",
          "MD",
          "UA",
          "AL",
          "BA",
          "HR",
          "ME",
          "MK",
          "RS",
          "SI",
          "KR",
          "BD",
          "PK",
          "LK",
          "GH",
          "KE",
          "NG",
          "TZ",
          "UG",
          "AG",
          "AM",
          "BS",
          "BB",
          "BZ",
          "BT",
          "BW",
          "BF",
          "CV",
          "CW",
          "DM",
          "FJ",
          "GM",
          "GE",
          "GD",
          "GW",
          "GY",
          "HT",
          "JM",
          "KI",
          "LS",
          "LR",
          "MW",
          "MV",
          "ML",
          "MH",
          "FM",
          "NA",
          "NR",
          "NE",
          "PW",
          "PG",
          "PR",
          "WS",
          "SM",
          "ST",
          "SN",
          "SC",
          "SL",
          "SB",
          "KN",
          "LC",
          "VC",
          "SR",
          "TL",
          "TO",
          "TT",
          "TV",
          "VU",
          "AZ",
          "BN",
          "BI",
          "KH",
          "CM",
          "TD",
          "KM",
          "GQ",
          "SZ",
          "GA",
          "GN",
          "KG",
          "LA",
          "MO",
          "MR",
          "MN",
          "NP",
          "RW",
          "TG",
          "UZ",
          "ZW",
          "BJ",
          "MG",
          "MU",
          "MZ",
          "AO",
          "CI",
          "DJ",
          "ZM",
          "CD",
          "CG",
          "IQ",
          "LY",
          "TJ",
          "VE",
          "ET",
          "XK"
        ],
        "external_urls": {
          "spotify": "https://open.spotify.com/album/79SqMfih2FN1NaLtZUcccG"
        },
        "href": "https://api.spotify.com/v1/albums/79SqMfih2FN1NaLtZUcccG",
        "id": "79SqMfih2FN1NaLtZUcccG",
        "images": [
          {
            "height": 640,
            "url": "https://i.scdn.co/image/ab67616d0000b273898c38365913cbb23fe50d9d",
            "width": 640
          },
          {
            "height": 300,
            "url": "https://i.scdn.co/image/ab67616d00001e02898c38365913cbb23fe50d9d",
            "width": 300
          },
          {
            "height": 64,
            "url": "https://i.scdn.co/image/ab67616d00004851898c38365913cbb23fe50d9d",
            "width": 64
          }
        ],
        "is_playable": true,
        "name": "Louder, Please",
        "release_date": "2025-01-17",
        "release_date_precision": "day",
        "total_tracks": 12,
        "type": "album",
        "uri": "spotify:album:79SqMfih2FN1NaLtZUcccG"
      },
      "artists": [
        {
          "external_urls": {
            "spotify": "https://open.spotify.com/artist/5YYrWH3w4JYijU4JZrOXWA"
          },
          "href": "https://api.spotify.com/v1/artists/5YYrWH3w4JYijU4JZrOXWA",
          "id": "5YYrWH3w4JYijU4JZrOXWA",
          "name": "Rose Gray",
          "type": "artist",
          "uri": "spotify:artist:5YYrWH3w4JYijU4JZrOXWA"
        }
      ],
      "available_markets": [
        "AR",
        "AU",
        "AT",
        "BE",
        "BO",
        "BR",
        "BG",
        "CA",
        "CL",
        "CO",
        "CR",
        "CY",
        "CZ",
        "DK",
        "DO",
        "DE",
        "EC",
        "EE",
        "SV",
        "FI",
        "FR",
        "GR",
        "GT",
        "HN",
        "HK",
        "HU",
        "IS",
        "IE",
        "IT",
        "LV",
        "LT",
        "LU",
        "MY",
        "MT",
        "MX",
        "NL",
        "NZ",
        "NI",
        "NO",
        "PA",
        "PY",
        "PE",
        "PH",
        "PL",
        "PT",
        "SG",
        "SK",
        "ES",
        "SE",
        "CH",
        "TW",
        "TR",
        "UY",
        "US",
        "GB",
        "AD",
        "LI",
        "MC",
        "ID",
        "JP",
        "TH",
        "VN",
        "RO",
        "IL",
        "ZA",
        "SA",
        "AE",
        "BH",
        "QA",
        "OM",
        "KW",
        "EG",
        "MA",
        "DZ",
        "TN",
        "LB",
        "JO",
        "PS",
        "IN",
        "BY",
        "KZ",
        "MD",
        "UA",
        "AL",
        "BA",
        "HR",
        "ME",
        "MK",
        "RS",
        "SI",
        "KR",
        "BD",
        "PK",
        "LK",
        "GH",
        "KE",
        "NG",
        "TZ",
        "UG",
        "AG",
        "AM",
        "BS",
        "BB",
        "BZ",
        "BT",
        "BW",
        "BF",
        "CV",
        "CW",
        "DM",
        "FJ",
        "GM",
        "GE",
        "GD",
        "GW",
        "GY",
        "HT",
        "JM",
        "KI",
        "LS",
        "LR",
        "MW",
        "MV",
        "ML",
        "MH",
        "FM",
        "NA",
        "NR",
        "NE",
        "PW",
        "PG",
        "PR",
        "WS",
        "SM",
        "ST",
        "SN",
        "SC",
        "SL",
        "SB",
        "KN",
        "LC",
        "VC",
        "SR",
        "TL",
        "TO",
        "TT",
        "TV",
        "VU",
        "AZ",
        "BN",
        "BI",
        "KH",
        "CM",
        "TD",
        "KM",
        "GQ",
        "SZ",
        "GA",
        "GN",
        "KG",
        "LA",
        "MO",
        "MR",
        "MN",
        "NP",
        "RW",
        "TG",
        "UZ",
        "ZW",
        "BJ",
        "MG",
        "MU",
        "MZ",
        "AO",
        "CI",
        "DJ",
        "ZM",
        "CD",
        "CG",
        "IQ",
        "LY",
        "TJ",
        "VE",
        "ET",
        "XK"
      ],
      "disc_number": 1,
      "duration_ms": 196581,
      "explicit": false,
      "external_ids": {
        "isrc": "GBENL2404086"
      },
      "external_urls": {
        "spotify": "https://open.spotify.com/track/6sNqy7jQPZeIquoajpf6rF"
      },
      "href": "https://api.spotify.com/v1/tracks/6sNqy7jQPZeIquoajpf6rF",
      "id": "6sNqy7jQPZeIquoajpf6rF",
      "is_local": false,
      "is_playable": true,
      "name": "Tectonic",
      "popularity": 45,
      "preview_url": null,
      "track_number": 5,
      "type": "track",
      "uri": "spotify:track:6sNqy7jQPZeIquoajpf6rF"
    },
    {
      "album": {
        "album_type": "album",
        "artists": [
          {
            "external_urls": {
              "spotify": "https://open.spotify.com/artist/49haq8aaaDI1pXbY1XcQaK"
            },
            "href": "https://api.spotify.com/v1/artists/49haq8aaaDI1pXbY1XcQaK",
            "id": "49haq8aaaDI1pXbY1XcQaK",
            "name": "Kaeto",
            "type": "artist",
            "uri": "spotify:artist:49haq8aaaDI1pXbY1XcQaK"
          }
        ],
        "available_markets": [
          "AR",
          "AU",
          "AT",
          "BE",
          "BO",
          "BR",
          "BG",
          "CA",
          "CL",
          "CO",
          "CR",
          "CY",
          "CZ",
          "DK",
          "DO",
          "DE",
          "EC",
          "EE",
          "SV",
          "FI",
          "FR",
          "GR",
          "GT",
          "HN",
          "HK",
          "HU",
          "IS",
          "IE",
          "IT",
          "LV",
          "LT",
          "LU",
          "MY",
          "MT",
          "MX",
          "NL",
          "NZ",
          "NI",
          "NO",
          "PA",
          "PY",
          "PE",
          "PH",
          "PL",
          "PT",
          "SG",
          "SK",
          "ES",
          "SE",
          "CH",
          "TW",
          "TR",
          "UY",
          "US",
          "GB",
          "AD",
          "LI",
          "MC",
          "ID",
          "JP",
          "TH",
          "VN",
          "RO",
          "IL",
          "ZA",
          "SA",
          "AE",
          "BH",
          "QA",
          "OM",
          "KW",
          "EG",
          "MA",
          "DZ",
          "TN",
          "LB",
          "JO",
          "PS",
          "IN",
          "KZ",
          "MD",
          "UA",
          "AL",
          "BA",
          "HR",
          "ME",
          "MK",
          "RS",
          "SI",
          "KR",
          "BD",
          "PK",
          "LK",
          "GH",
          "KE",
          "NG",
          "TZ",
          "UG",
          "AG",
          "AM",
          "BS",
          "BB",
          "BZ",
          "BT",
          "BW",
          "BF",
          "CV",
          "CW",
          "DM",
          "FJ",
          "GM",
          "GE",
          "GD",
          "GW",
          "GY",
          "HT",
          "JM",
          "KI",
          "LS",
          "LR",
          "MW",
          "MV",
          "ML",
          "MH",
          "FM",
          "NA",
          "NR",
          "NE",
          "PW",
          "PG",
          "WS",
          "SM",
          "ST",
          "SN",
          "SC",
          "SL",
          "SB",
          "KN",
          "LC",
          "VC",
          "SR",
          "TL",
          "TO",
          "TT",
          "TV",
          "VU",
          "AZ",
          "BN",
          "BI",
          "KH",
          "CM",
          "TD",
          "KM",
          "GQ",
          "SZ",
          "GA",
          "GN",
          "KG",
          "LA",
          "MO",
          "MR",
          "MN",
          "NP",
          "RW",
          "TG",
          "UZ",
          "ZW",
          "BJ",
          "MG",
          "MU",
          "MZ",
          "AO",
          "CI",
          "DJ",
          "ZM",
          "CD",
          "CG",
          "IQ",
          "LY",
          "TJ",
          "VE",
          "ET",
          "XK"
        ],
        "external_urls": {
          "spotify": "https://open.spotify.com/album/6nLhO0HjISaaG6Snxi8nMF"
        },
        "href": "https://api.spotify.com/v1/albums/6nLhO0HjISaaG6Snxi8nMF",
        "id": "6nLhO0HjISaaG6Snxi8nMF",
        "images": [
          {
            "height": 640,
            "url": "https://i.scdn.co/image/ab67616d0000b273de64b43dc7e9e13163fbae5f",
            "width": 640
          },
          {
            "height": 300,
            "url": "https://i.scdn.co/image/ab67616d00001e02de64b43dc7e9e13163fbae5f",
            "width": 300
          },
          {
            "height": 64,
            "url": "https://i.scdn.co/image/ab67616d00004851de64b43dc7e9e13163fbae5f",
            "width": 64
          }
        ],
        "is_playable": true,
        "name": "INTRO",
        "release_date": "2024-09-20",
        "release_date_precision": "day",
        "total_tracks": 8,
        "type": "album",
        "uri": "spotify:album:6nLhO0HjISaaG6Snxi8nMF"
      },
      "artists": [
        {
          "external_urls": {
            "spotify": "https://open.spotify.com/artist/49haq8aaaDI1pXbY1XcQaK"
          },
          "href": "https://api.spotify.com/v1/artists/49haq8aaaDI1pXbY1XcQaK",
          "id": "49haq8aaaDI1pXbY1XcQaK",
          "name": "Kaeto",
          "type": "artist",
          "uri": "spotify:artist:49haq8aaaDI1pXbY1XcQaK"
        }
      ],
      "available_markets": [
        "AR",
        "AU",
        "AT",
        "BE",
        "BO",
        "BR",
        "BG",
        "CA",
        "CL",
        "CO",
        "CR",
        "CY",
        "CZ",
        "DK",
        "DO",
        "DE",
        "EC",
        "EE",
        "SV",
        "FI",
        "FR",
        "GR",
        "GT",
        "HN",
        "HK",
        "HU",
        "IS",
        "IE",
        "IT",
        "LV",
        "LT",
        "LU",
        "MY",
        "MT",
        "MX",
        "NL",
        "NZ",
        "NI",
        "NO",
        "PA",
        "PY",
        "PE",
        "PH",
        "PL",
        "PT",
        "SG",
        "SK",
        "ES",
        "SE",
        "CH",
        "TW",
        "TR",
        "UY",
        "US",
        "GB",
        "AD",
        "LI",
        "MC",
        "ID",
        "JP",
        "TH",
        "VN",
        "RO",
        "IL",
        "ZA",
        "SA",
        "AE",
        "BH",
        "QA",
        "OM",
        "KW",
        "EG",
        "MA",
        "DZ",
        "TN",
        "LB",
        "JO",
        "PS",
        "IN",
        "KZ",
        "MD",
        "UA",
        "AL",
        "BA",
        "HR",
        "ME",
        "MK",
        "RS",
        "SI",
        "KR",
        "BD",
        "PK",
        "LK",
        "GH",
        "KE",
        "NG",
        "TZ",
        "UG",
        "AG",
        "AM",
        "BS",
        "BB",
        "BZ",
        "BT",
        "BW",
        "BF",
        "CV",
        "CW",
        "DM",
        "FJ",
        "GM",
        "GE",
        "GD",
        "GW",
        "GY",
        "HT",
        "JM",
        "KI",
        "LS",
        "LR",
        "MW",
        "MV",
        "ML",
        "MH",
        "FM",
        "NA",
        "NR",
        "NE",
        "PW",
        "PG",
        "WS",
        "SM",
        "ST",
        "SN",
        "SC",
        "SL",
        "SB",
        "KN",
        "LC",
        "VC",
        "SR",
        "TL",
        "TO",
        "TT",
        "TV",
        "VU",
        "AZ",
        "BN",
        "BI",
        "KH",
        "CM",
        "TD",
        "KM",
        "GQ",
        "SZ",
        "GA",
        "GN",
        "KG",
        "LA",
        "MO",
        "MR",
        "MN",
        "NP",
        "RW",
        "TG",
        "UZ",
        "ZW",
        "BJ",
        "MG",
        "MU",
        "MZ",
        "AO",
        "CI",
        "DJ",
        "ZM",
        "CD",
        "CG",
        "IQ",
        "LY",
        "TJ",
        "VE",
        "ET",
        "XK"
      ],
      "disc_number": 1,
      "duration_ms": 238614,
      "explicit": false,
      "external_ids": {
        "isrc": "GBUM72400842"
      },
      "external_urls": {
        "spotify": "https://open.spotify.com/track/1KXDVRtn02mymQDmbPdTl7"
      },
      "href": "https://api.spotify.com/v1/tracks/1KXDVRtn02mymQDmbPdTl7",
      "id": "1KXDVRtn02mymQDmbPdTl7",
      "is_local": false,
      "is_playable": true,
      "name": "HERO",
      "popularity": 31,
      "preview_url": null,
      "track_number": 6,
      "type": "track",
      "uri": "spotify:track:1KXDVRtn02mymQDmbPdTl7"
    },
    {
      "album": {
        "album_type": "album",
        "artists": [
          {
            "external_urls": {
              "spotify": "https://open.spotify.com/artist/2rLGlNI6htigNxx172qxLu"
            },
            "href": "https://api.spotify.com/v1/artists/2rLGlNI6htigNxx172qxLu",
            "id": "2rLGlNI6htigNxx172qxLu",
            "name": "Jane Remover",
            "type": "artist",
            "uri": "spotify:artist:2rLGlNI6htigNxx172qxLu"
          }
        ],
        "available_markets": [
          "AR",
          "AU",
          "AT",
          "BE",
          "BO",
          "BR",
          "BG",
          "CA",
          "CL",
          "CO",
          "CR",
          "CY",
          "CZ",
          "DK",
          "DO",
          "DE",
          "EC",
          "EE",
          "SV",
          "FI",
          "FR",
          "GR",
          "GT",
          "HN",
          "HK",
          "HU",
          "IS",
          "IE",
          "IT",
          "LV",
          "LT",
          "LU",
          "MY",
          "MT",
          "MX",
          "NL",
          "NZ",
          "NI",
          "NO",
          "PA",
          "PY",
          "PE",
          "PH",
          "PL",
          "PT",
          "SG",
          "SK",
          "ES",
          "SE",
          "CH",
          "TW",
          "TR",
          "UY",
          "US",
          "GB",
          "AD",
          "LI",
          "MC",
          "ID",
          "JP",
          "TH",
          "VN",
          "RO",
          "IL",
          "ZA",
          "SA",
          "AE",
          "BH",
          "QA",
          "OM",
          "KW",
          "EG",
          "MA",
          "DZ",
          "TN",
          "LB",
          "JO",
          "PS",
          "IN",
          "BY",
          "KZ",
          "MD",
          "UA",
          "AL",
          "BA",
          "HR",
          "ME",
          "MK",
          "RS",
          "SI",
          "KR",
          "BD",
          "PK",
          "LK",
          "GH",
          "KE",
          "NG",
          "TZ",
          "UG",
          "AG",
          "AM",
          "BS",
          "BB",
          "BZ",
          "BT",
          "BW",
          "BF",
          "CV",
          "CW",
          "DM",
          "FJ",
          "GM",
          "GE",
          "GD",
          "GW",
          "GY",
          "HT",
          "JM",
          "KI",
          "LS",
          "LR",
          "MW",
          "MV",
          "ML",
          "MH",
          "FM",
          "NA",
          "NR",
          "NE",
          "PW",
          "PG",
          "PR",
          "WS",
          "SM",
          "ST",
          "SN",
          "SC",
          "SL",
          "SB",
          "KN",
          "LC",
          "VC",
          "SR",
          "TL",
          "TO",
          "TT",
          "TV",
          "VU",
          "AZ",
          "BN",
          "BI",
          "KH",
          "CM",
          "TD",
          "KM",
          "GQ",
          "SZ",
          "GA",
          "GN",
          "KG",
          "LA",
          "MO",
          "MR",
          "MN",
          "NP",
          "RW",
          "TG",
          "UZ",
          "ZW",
          "BJ",
          "MG",
          "MU",
          "MZ",
          "AO",
          "CI",
          "DJ",
          "ZM",
          "CD",
          "CG",
          "IQ",
          "LY",
          "TJ",
          "VE",
          "ET",
          "XK"
        ],
        "external_urls": {
          "spotify": "https://open.spotify.com/album/21b4cDNse2AMpj94ykfuON"
        },
        "href": "https://api.spotify.com/v1/albums/21b4cDNse2AMpj94ykfuON",
        "id": "21b4cDNse2AMpj94ykfuON",
        "images": [
          {
            "height": 640,
            "url": "https://i.scdn.co/image/ab67616d0000b273ab0d83b752dcf9f2a7ddd51b",
            "width": 640
          },
          {
            "height": 300,
            "url": "https://i.scdn.co/image/ab67616d00001e02ab0d83b752dcf9f2a7ddd51b",
            "width": 300
          },
          {
            "height": 64,
            "url": "https://i.scdn.co/image/ab67616d00004851ab0d83b752dcf9f2a7ddd51b",
            "width": 64
          }
        ],
        "is_playable": true,
        "name": "Revengeseekerz",
        "release_date": "2025-04-04",
        "release_date_precision": "day",
        "total_tracks": 12,
        "type": "album",
        "uri": "spotify:album:21b4cDNse2AMpj94ykfuON"
      },
      "artists": [
        {
          "external_urls": {
            "spotify": "https://open.spotify.com/artist/2rLGlNI6htigNxx172qxLu"
          },
          "href": "https://api.spotify.com/v1/artists/2rLGlNI6htigNxx172qxLu",
          "id": "2rLGlNI6htigNxx172qxLu",
          "name": "Jane Remover",
          "type": "artist",
          "uri": "spotify:artist:2rLGlNI6htigNxx172qxLu"
        }
      ],
      "available_markets": [
        "AR",
        "AU",
        "AT",
        "BE",
        "BO",
        "BR",
        "BG",
        "CA",
        "CL",
        "CO",
        "CR",
        "CY",
        "CZ",
        "DK",
        "DO",
        "DE",
        "EC",
        "EE",
        "SV",
        "FI",
        "FR",
        "GR",
        "GT",
        "HN",
        "HK",
        "HU",
        "IS",
        "IE",
        "IT",
        "LV",
        "LT",
        "LU",
        "MY",
        "MT",
        "MX",
        "NL",
        "NZ",
        "NI",
        "NO",
        "PA",
        "PY",
        "PE",
        "PH",
        "PL",
        "PT",
        "SG",
        "SK",
        "ES",
        "SE",
        "CH",
        "TW",
        "TR",
        "UY",
        "US",
        "GB",
        "AD",
        "LI",
        "MC",
        "ID",
        "JP",
        "TH",
        "VN",
        "RO",
        "IL",
        "ZA",
        "SA",
        "AE",
        "BH",
        "QA",
        "OM",
        "KW",
        "EG",
        "MA",
        "DZ",
        "TN",
        "LB",
        "JO",
        "PS",
        "IN",
        "BY",
        "KZ",
        "MD",
        "UA",
        "AL",
        "BA",
        "HR",
        "ME",
        "MK",
        "RS",
        "SI",
        "KR",
        "BD",
        "PK",
        "LK",
        "GH",
        "KE",
        "NG",
        "TZ",
        "UG",
        "AG",
        "AM",
        "BS",
        "BB",
        "BZ",
        "BT",
        "BW",
        "BF",
        "CV",
        "CW",
        "DM",
        "FJ",
        "GM",
        "GE",
        "GD",
        "GW",
        "GY",
        "HT",
        "JM",
        "KI",
        "LS",
        "LR",
        "MW",
        "MV",
        "ML",
        "MH",
        "FM",
        "NA",
        "NR",
        "NE",
        "PW",
        "PG",
        "PR",
        "WS",
        "SM",
        "ST",
        "SN",
        "SC",
        "SL",
        "SB",
        "KN",
        "LC",
        "VC",
        "SR",
        "TL",
        "TO",
        "TT",
        "TV",
        "VU",
        "AZ",
        "BN",
        "BI",
        "KH",
        "CM",
        "TD",
        "KM",
        "GQ",
        "SZ",
        "GA",
        "GN",
        "KG",
        "LA",
        "MO",
        "MR",
        "MN",
        "NP",
        "RW",
        "TG",
        "UZ",
        "ZW",
        "BJ",
        "MG",
        "MU",
        "MZ",
        "AO",
        "CI",
        "DJ",
        "ZM",
        "CD",
        "CG",
        "IQ",
        "LY",
        "TJ",
        "VE",
        "ET",
        "XK"
      ],
      "disc_number": 1,
      "duration_ms": 236571,
      "explicit": true,
      "external_ids": {
        "isrc": "QM24S2501670"
      },
      "external_urls": {
        "spotify": "https://open.spotify.com/track/2AjTT2CBthpsIQtyxzhSr4"
      },
      "href": "https://api.spotify.com/v1/tracks/2AjTT2CBthpsIQtyxzhSr4",
      "id": "2AjTT2CBthpsIQtyxzhSr4",
      "is_local": false,
      "is_playable": true,
      "name": "Professional Vengeance",
      "popularity": 57,
      "preview_url": null,
      "track_number": 10,
      "type": "track",
      "uri": "spotify:track:2AjTT2CBthpsIQtyxzhSr4"
    },
    {
      "album": {
        "album_type": "album",
        "artists": [
          {
            "external_urls": {
              "spotify": "https://open.spotify.com/artist/3dz0NnIZhtKKeXZxLOxCam"
            },
            "href": "https://api.spotify.com/v1/artists/3dz0NnIZhtKKeXZxLOxCam",
            "id": "3dz0NnIZhtKKeXZxLOxCam",
            "name": "Porter Robinson",
            "type": "artist",
            "uri": "spotify:artist:3dz0NnIZhtKKeXZxLOxCam"
          }
        ],
        "available_markets": [
          "JP"
        ],
        "external_urls": {
          "spotify": "https://open.spotify.com/album/4btev9CC7D5soKdcIP6ApM"
        },
        "href": "https://api.spotify.com/v1/albums/4btev9CC7D5soKdcIP6ApM",
        "id": "4btev9CC7D5soKdcIP6ApM",
        "images": [
          {
            "height": 640,
            "url": "https://i.scdn.co/image/ab67616d0000b273a6de55fe4c950e6e4910f781",
            "width": 640
          },
          {
            "height": 300,
            "url": "https://i.scdn.co/image/ab67616d00001e02a6de55fe4c950e6e4910f781",
            "width": 300
          },
          {
            "height": 64,
            "url": "https://i.scdn.co/image/ab67616d00004851a6de55fe4c950e6e4910f781",
            "width": 64
          }
        ],
        "is_playable": true,
        "name": "Nurture",
        "release_date": "2021-04-23",
        "release_date_precision": "day",
        "total_tracks": 15,
        "type": "album",
        "uri": "spotify:album:4btev9CC7D5soKdcIP6ApM"
      },
      "artists": [
        {
          "external_urls": {
            "spotify": "https://open.spotify.com/artist/3dz0NnIZhtKKeXZxLOxCam"
          },
          "href": "https://api.spotify.com/v1/artists/3dz0NnIZhtKKeXZxLOxCam",
          "id": "3dz0NnIZhtKKeXZxLOxCam",
          "name": "Porter Robinson",
          "type": "artist",
          "uri": "spotify:artist:3dz0NnIZhtKKeXZxLOxCam"
        }
      ],
      "available_markets": [
        "JP"
      ],
      "disc_number": 1,
      "duration_ms": 218509,
      "explicit": false,
      "external_ids": {
        "isrc": "USQE92000001"
      },
      "external_urls": {
        "spotify": "https://open.spotify.com/track/3xIucxNeIoI0UoiBl3TtH9"
      },
      "href": "https://api.spotify.com/v1/tracks/3xIucxNeIoI0UoiBl3TtH9",
      "id": "3xIucxNeIoI0UoiBl3TtH9",
      "is_local": false,
      "is_playable": true,
      "name": "Get Your Wish",
      "popularity": 30,
      "preview_url": null,
      "track_number": 3,
      "type": "track",
      "uri": "spotify:track:3xIucxNeIoI0UoiBl3TtH9"
    }
  ],
  "lastUpdated": "2025-07-13T19:56:33.323Z",
  "cacheExpiry": "2025-07-14T01:56:33.323Z"
}